llama_index/storage/docstore/azurecosmosnosql/__init__.py
llama_index/storage/docstore/azurecosmosnosql/base.py
llama_index_storage_docstore_azurecosmosnosql-1.2.1.dist-info/METADATA
llama_index_storage_docstore_azurecosmosnosql-1.2.1.dist-info/WHEEL
llama_index_storage_docstore_azurecosmosnosql-1.2.1.dist-info/licenses/LICENSE
llama_index_storage_docstore_azurecosmosnosql-1.2.1.dist-info/RECORD
